content_settings/__init__.py
content_settings/admin.py
content_settings/apps.py
content_settings/cache_triggers.py
content_settings/caching.py
content_settings/conf.py
content_settings/context_managers.py
content_settings/context_processors.py
content_settings/defaults/collections.py
content_settings/defaults/context.py
content_settings/defaults/filters.py
content_settings/defaults/modifiers.py
content_settings/export.py
content_settings/fields.py
content_settings/functools.py
content_settings/management/commands/content_settings_export.py
content_settings/management/commands/content_settings_import.py
content_settings/management/commands/content_settings_migrate.py
content_settings/middlewares.py
content_settings/migrate.py
content_settings/migrations/0001_initial.py
content_settings/migrations/0002_user_defined.py
content_settings/migrations/0003_user_preview.py
content_settings/migrations/0004_userdefined_preview.py
content_settings/migrations/__init__.py
content_settings/models.py
content_settings/permissions.py
content_settings/receivers.py
content_settings/settings.py
content_settings/store.py
content_settings/tags.py
content_settings/templates/admin/content_settings/contentsetting/change_form.html
content_settings/templates/admin/content_settings/contentsetting/change_list.html
content_settings/templates/admin/content_settings/contentsetting/context_tags.html
content_settings/templates/admin/content_settings/contentsetting/import_json.html
content_settings/templates/admin/content_settings/contentsetting/pagination.html
content_settings/templates/admin/content_settings/contentsetting/submit_line.html
content_settings/templatetags/__init__.py
content_settings/templatetags/content_settings_admin.py
content_settings/templatetags/content_settings_extras.py
content_settings/tests/test_all_settings.py
content_settings/types/__init__.py
content_settings/types/array.py
content_settings/types/basic.py
content_settings/types/datetime.py
content_settings/types/each.py
django_content_settings-0.29.2.dist-info/LICENSE
django_content_settings-0.29.2.dist-info/METADATA
django_content_settings-0.29.2.dist-info/WHEEL
django_content_settings-0.29.2.dist-info/RECORD
