Metadata-Version: 2.1
Name: django-content-settings
Version: 0.29.2
Summary: DCS - the most advanced admin editable setting
Home-page: https://django-content-settings.readthedocs.io/
License: MIT
Keywords: Django,settings
Author: oduvan
Author-email: a.lyabah@checkio.org
Requires-Python: >=3.8
Classifier: Framework :: Django :: 3.2
Classifier: Framework :: Django :: 4
Classifier: Framework :: Django :: 4.0
Classifier: Framework :: Django :: 4.1
Classifier: Framework :: Django :: 4.2
Classifier: Framework :: Django :: 5.0
Classifier: Framework :: Django :: 5.1
Classifier: License :: OSI Approved :: MIT License
Classifier: Programming Language :: Python :: 3
Classifier: Programming Language :: Python :: 3.8
Classifier: Programming Language :: Python :: 3.9
Classifier: Programming Language :: Python :: 3.10
Classifier: Programming Language :: Python :: 3.11
Classifier: Programming Language :: Python :: 3.12
Classifier: Programming Language :: Python :: 3.13
Requires-Dist: django (>=3.2)
Project-URL: Repository, https://github.com/occipital/django-content-settings/
